remi_portal_gun/__init__.py
remi_portal_gun/access_static.py
remi_portal_gun/discovery.py
remi_portal_gun/faster.sh
remi_portal_gun/inject_json_into_js.py
remi_portal_gun/main.py
remi_portal_gun/server.py
remi_portal_gun/www/__init__.py
remi_portal_gun/www/assets/__init__.py
remi_portal_gun/www/assets/index.2b0816df.js
remi_portal_gun/www/assets/worker.a1038a5f.js
remi_portal_gun/www/favicon.ico
remi_portal_gun/www/index.html
remi_portal_gun-0.5.0.dist-info/entry_points.txt
remi_portal_gun-0.5.0.dist-info/WHEEL
remi_portal_gun-0.5.0.dist-info/METADATA
remi_portal_gun-0.5.0.dist-info/RECORD
